auger_ml/AugerMLPreprocessors.py
auger_ml/FSClient.py
auger_ml/LocalFSClient.py
auger_ml/S3FSClient.py
auger_ml/Utils.py
auger_ml/__init__.py
auger_ml/celery_logging.py
auger_ml/model_exporter.py
auger_ml/model_helper.py
auger_ml/model_review.py
auger_ml/probabilistic_counter.py
auger_ml/warmstart_optimizer.py
auger_ml/algorithms/__init__.py
auger_ml/algorithms/adam_wd.py
auger_ml/algorithms/baseline.py
auger_ml/algorithms/cat_boost.py
auger_ml/algorithms/dnn.py
auger_ml/algorithms/dnn_base.py
auger_ml/algorithms/dnn_res.py
auger_ml/algorithms/dnn_shaped.py
auger_ml/algorithms/keras_mem.py
auger_ml/algorithms/linear.py
auger_ml/algorithms/mlp.py
auger_ml/algorithms/svm.py
auger_ml/algorithms/timeseries.py
auger_ml/algorithms/ts_dnn.py
auger_ml/algorithms/ts_dnn_cpu.py
auger_ml/algorithms/ts_lstm.py
auger_ml/algorithms/utils.py
auger_ml/data_source/__init__.py
auger_ml/data_source/data_source_api.py
auger_ml/data_source/data_source_api_pandas.py
auger_ml/data_source/data_source_api_pandas_proxy.py
auger_ml/data_source/data_source_factory.py
auger_ml/data_source/group_splits.py
auger_ml/data_splitters/BaseSplitter.py
auger_ml/data_splitters/DFSparkDataPrep.py
auger_ml/data_splitters/SimpleSplitter.py
auger_ml/data_splitters/XYNumpyDataPrep.py
auger_ml/data_splitters/__init__.py
auger_ml/ensembles/__init__.py
auger_ml/ensembles/algorithms.py
auger_ml/ensembles/base.py
auger_ml/ensembles/build.py
auger_ml/ensembles/deep_ensemble.py
auger_ml/ensembles/deep_super_learner.py
auger_ml/ensembles/greedy_selection.py
auger_ml/ensembles/load_data.py
auger_ml/ensembles/metrics.py
auger_ml/ensembles/super_learner.py
auger_ml/ensembles/utils.py
auger_ml/ensembles/space/__init__.py
auger_ml/ensembles/space/classifier.py
auger_ml/ensembles/space/regressor.py
auger_ml/preprocessors/__init__.py
auger_ml/preprocessors/base.py
auger_ml/preprocessors/categorical.py
auger_ml/preprocessors/date_time.py
auger_ml/preprocessors/dim_reduction.py
auger_ml/preprocessors/eliminate.py
auger.ai.predict-1.1.13.dist-info/LICENSE
auger.ai.predict-1.1.13.dist-info/METADATA
auger.ai.predict-1.1.13.dist-info/WHEEL
auger.ai.predict-1.1.13.dist-info/top_level.txt
auger.ai.predict-1.1.13.dist-info/RECORD
