Metadata-Version: 2.1
Name: auger.ai.predict
Version: 1.1.13
Summary: Auger ML predict python and command line interface
Home-page: https://github.com/deeplearninc/auger-ai
Author: Deep Learn, Inc.
Author-email: augerai@dplrn.com
License: Apache
Keywords: augerai auger ai machine learning automl deeplearn api sdk prediction predict
Platform: any
Classifier: Development Status :: 3 - Alpha
Classifier: Intended Audience :: Developers
Classifier: Intended Audience :: System Administrators
Classifier: Topic :: Software Development :: Build Tools
Classifier: License :: OSI Approved :: MIT License
Classifier: Programming Language :: Python :: 3
Classifier: Programming Language :: Python :: 3.7
Classifier: Programming Language :: Python :: 3 :: Only
Requires-Python: >=3
Provides-Extra: all
Requires-Dist: numpy ==1.23.5 ; extra == 'all'
Requires-Dist: pandas ==1.5.0 ; extra == 'all'
Requires-Dist: six ==1.16.0 ; extra == 'all'
Requires-Dist: scipy ==1.9.3 ; extra == 'all'
Requires-Dist: scikit-learn ==1.2.0 ; extra == 'all'
Requires-Dist: xgboost ==1.6.2 ; extra == 'all'
Requires-Dist: catboost <2.0,>1.0 ; extra == 'all'
Requires-Dist: lightgbm <3.4,>3.3 ; extra == 'all'
Requires-Dist: modAL-python ; extra == 'all'
Requires-Dist: joblib ; extra == 'all'
Requires-Dist: boto3 ; extra == 'all'
Requires-Dist: s3fs ==0.4.2 ; extra == 'all'
Requires-Dist: stopit ; extra == 'all'
Requires-Dist: smart-open ==6.2.0 ; extra == 'all'
Requires-Dist: kombu ==5.2.4 ; extra == 'all'
Requires-Dist: celery ==5.2.7 ; extra == 'all'
Provides-Extra: no_cat_lgbm
Requires-Dist: numpy ==1.23.5 ; extra == 'no_cat_lgbm'
Requires-Dist: pandas ==1.5.0 ; extra == 'no_cat_lgbm'
Requires-Dist: six ==1.16.0 ; extra == 'no_cat_lgbm'
Requires-Dist: scipy ==1.9.3 ; extra == 'no_cat_lgbm'
Requires-Dist: scikit-learn ==1.2.0 ; extra == 'no_cat_lgbm'
Requires-Dist: xgboost ==1.6.2 ; extra == 'no_cat_lgbm'
Requires-Dist: modAL-python ; extra == 'no_cat_lgbm'
Requires-Dist: joblib ; extra == 'no_cat_lgbm'
Requires-Dist: boto3 ; extra == 'no_cat_lgbm'
Requires-Dist: s3fs ==0.4.2 ; extra == 'no_cat_lgbm'
Requires-Dist: stopit ; extra == 'no_cat_lgbm'
Requires-Dist: smart-open ==6.2.0 ; extra == 'no_cat_lgbm'
Requires-Dist: kombu ==5.2.4 ; extra == 'no_cat_lgbm'
Requires-Dist: celery ==5.2.7 ; extra == 'no_cat_lgbm'
